admin_two_factor/__init__.py
admin_two_factor/admin.py
admin_two_factor/apps.py
admin_two_factor/models.py
admin_two_factor/settings.py
admin_two_factor/tests.py
admin_two_factor/urls.py
admin_two_factor/utils.py
admin_two_factor/views.py
admin_two_factor/context_processors/__init__.py
admin_two_factor/context_processors/two_factor.py
admin_two_factor/migrations/0001_initial.py
admin_two_factor/migrations/0002_alter_twofactorverification_id.py
admin_two_factor/migrations/__init__.py
admin_two_factor/static/two_step_assets/css/jquery-confirm.min.css
admin_two_factor/static/two_step_assets/jquery-cookie/.gitignore
admin_two_factor/static/two_step_assets/jquery-cookie/.jshintrc
admin_two_factor/static/two_step_assets/jquery-cookie/.tm_properties
admin_two_factor/static/two_step_assets/jquery-cookie/.travis.yml
admin_two_factor/static/two_step_assets/jquery-cookie/CHANGELOG.md
admin_two_factor/static/two_step_assets/jquery-cookie/CONTRIBUTING.md
admin_two_factor/static/two_step_assets/jquery-cookie/Gruntfile.js
admin_two_factor/static/two_step_assets/jquery-cookie/MIT-LICENSE.txt
admin_two_factor/static/two_step_assets/jquery-cookie/README.md
admin_two_factor/static/two_step_assets/jquery-cookie/bower.json
admin_two_factor/static/two_step_assets/jquery-cookie/component.json
admin_two_factor/static/two_step_assets/jquery-cookie/cookie.jquery.json
admin_two_factor/static/two_step_assets/jquery-cookie/jquery.cookie.js
admin_two_factor/static/two_step_assets/jquery-cookie/package.json
admin_two_factor/static/two_step_assets/js/jquery-3.5.1.min.js
admin_two_factor/static/two_step_assets/js/jquery-confirm.min.js
admin_two_factor/static/two_step_assets/js/verification.js
admin_two_factor/templates/admin/base.html
admin_two_factor/templates/admin/login.html
admin_two_factor/templates/two_step_verification/admin/qrcode.html
django_admin_two_factorv2-0.1.3.dist-info/licenses/LICENSE
django_admin_two_factorv2-0.1.3.dist-info/METADATA
django_admin_two_factorv2-0.1.3.dist-info/WHEEL
django_admin_two_factorv2-0.1.3.dist-info/top_level.txt
django_admin_two_factorv2-0.1.3.dist-info/RECORD
